data/Fly80XY_norm_1061.csv
dimx-1.1.1.dist-info/METADATA
dimx-1.1.1.dist-info/WHEEL
dimx-1.1.1.dist-info/entry_points.txt
dimx-1.1.1.dist-info/licenses/LICENSE
dimx/CLI_Parser.py
dimx/CrossMapColumns.py
dimx/Evaluate.py
dimx/MDE.py
dimx/ManifoldDimExpand.py
dimx/Run.py
dimx/__init__.py
example/.ipynb_checkpoints/MDE_Fly_Example-checkpoint.ipynb
example/Evaluate_Fly.png
example/MDE_Fly.png
example/MDE_Fly_Example.ipynb
dimx-1.1.1.dist-info/RECORD
