Metadata-Version: 2.4
Name: dimx
Version: 1.1.1
Summary: Manifold Dimensional Expansion
Author-Email: Joseph Park <JosephPark@IEEE.org>, Gerald Pao <Gerald.Pao@OIST.jp>, Temma Fujishige <Temma.Fujishige@OIST.jp>
License-Expression: LicenseRef-OIST-License
License-File: LICENSE
Classifier: Programming Language :: Python :: 3
Classifier: Operating System :: OS Independent
Project-URL: Homepage, https://github.com/pao-unit/MDE
Project-URL: Documentation, https://pao-unit.github.io/MDE_docs/
Project-URL: Issues, https://github.com/pao-unit/MDE/issues
Requires-Python: >=3.11
Requires-Dist: pyEDM>=2.2.3
Requires-Dist: matplotlib
Requires-Dist: numpy
Requires-Dist: pandas>=2.0
Requires-Dist: pydiffmap>=0.2.0.1
Requires-Dist: scikit-learn
Requires-Dist: scipy
